[
  {
    "type": "skill_boost",
    "stat": "str",
    "skills": [ "mechanics", "swimming", "bashing", "cutting", "melee", "throw" ],
    "skill_offset": -4,
    "scaling_power": 0.2
  },
  {
    "type": "skill_boost",
    "stat": "dex",
    "skills": [ "driving", "survival", "tailor", "traps", "dodge", "stabbing", "unarmed" ],
    "skill_offset": -4,
    "scaling_power": 0.2
  },
  {
    "type": "skill_boost",
    "stat": "int",
    "skills": [ "computer", "cooking", "electronics", "fabrication", "firstaid", "speech", "chemistry", "metaphysics", "gramayre" ],
    "skill_offset": -4,
    "scaling_power": 0.1
  },
  {
    "type": "skill_boost",
    "stat": "per",
    "skills": [ "archery", "gun", "launcher", "pistol", "rifle", "shotgun", "smg", "deduction" ],
    "skill_offset": -4,
    "scaling_power": 0.1
  }
]
