[
  {
    "result": "lsurvivor_pants",
    "type": "recipe",
    "activity_level": "LIGHT_EXERCISE",
    "category": "CC_*",
    "subcategory": "CSC_*_NESTED",
    "skill_used": "tailor",
    "difficulty": 5,
    "skills_required": [ "fabrication", 6 ],
    "time": "12 h",
    "autolearn": true,
    "using": [
      [ "tailoring_cotton_patchwork", 2 ],
      [ "waterproofing_plastic_sheets", 8 ],
      [ "tailoring_kevlar_fabric", 4 ],
      [ "fastener_small", 1 ]
    ],
    "proficiencies": [
      { "proficiency": "prof_closures" },
      { "proficiency": "prof_closures_waterproofing" },
      { "proficiency": "prof_polymerworking" }
    ],
    "components": [
      [
        [ "legrig", 1 ],
        [ "tool_belt", 1 ],
        [ "ragpouch", 4 ],
        [ "leather_pouch", 2 ],
        [ "dump_pouch", 1 ],
        [ "purse", 2 ],
        [ "fanny", 2 ]
      ]
    ]
  },
  {
    "result": "xs_lsurvivor_pants",
    "type": "recipe",
    "copy-from": "lsurvivor_pants",
    "time": "12 h",
    "using": [
      [ "tailoring_cotton_patchwork", 1 ],
      [ "waterproofing_plastic_sheets", 6 ],
      [ "tailoring_kevlar_fabric", 3 ],
      [ "fastener_small", 1 ]
    ],
    "components": [
      [
        [ "legrig", 2 ],
        [ "tool_belt", 2 ],
        [ "ragpouch", 4 ],
        [ "leather_pouch", 2 ],
        [ "dump_pouch", 1 ],
        [ "purse", 2 ],
        [ "fanny", 2 ]
      ]
    ]
  },
  {
    "result": "xl_lsurvivor_pants",
    "type": "recipe",
    "copy-from": "lsurvivor_pants",
    "time": "13 h 30 m",
    "using": [
      [ "tailoring_cotton_patchwork", 4 ],
      [ "waterproofing_plastic_sheets", 10 ],
      [ "tailoring_kevlar_fabric", 6 ],
      [ "fastener_small", 1 ]
    ],
    "components": [
      [
        [ "legrig", 1 ],
        [ "tool_belt", 1 ],
        [ "ragpouch", 4 ],
        [ "leather_pouch", 2 ],
        [ "dump_pouch", 1 ],
        [ "purse", 2 ],
        [ "fanny", 2 ]
      ]
    ]
  },
  {
    "result": "pants_survivor",
    "type": "recipe",
    "activity_level": "LIGHT_EXERCISE",
    "category": "CC_*",
    "subcategory": "CSC_*_NESTED",
    "skill_used": "tailor",
    "difficulty": 6,
    "skills_required": [ "fabrication", 5 ],
    "time": "14 h",
    "autolearn": true,
    "using": [
      [ "tailoring_kevlar_fabric", 4 ],
      [ "tailoring_cotton", 5 ],
      [ "waterproofing_plastic_sheets", 8 ],
      [ "fastener_small", 1 ]
    ],
    "proficiencies": [
      { "proficiency": "prof_closures" },
      { "proficiency": "prof_closures_waterproofing" },
      { "proficiency": "prof_polymerworking" }
    ],
    "components": [
      [ [ "pants_army", 1 ], [ "pants_cargo", 1 ] ],
      [
        [ "tacvest", 1 ],
        [ "legrig", 1 ],
        [ "vest", 1 ],
        [ "tool_belt", 1 ],
        [ "ragpouch", 4 ],
        [ "leather_pouch", 2 ],
        [ "dump_pouch", 1 ],
        [ "purse", 2 ],
        [ "fanny", 2 ]
      ]
    ]
  },
  {
    "result": "xs_pants_survivor",
    "type": "recipe",
    "copy-from": "pants_survivor",
    "time": "14 h",
    "using": [
      [ "tailoring_kevlar_fabric", 3 ],
      [ "tailoring_cotton", 3 ],
      [ "waterproofing_plastic_sheets", 6 ],
      [ "fastener_small", 1 ]
    ],
    "components": [
      [ [ "pants_army", 1 ], [ "pants_cargo", 1 ] ],
      [
        [ "tacvest", 1 ],
        [ "legrig", 1 ],
        [ "vest", 1 ],
        [ "tool_belt", 1 ],
        [ "ragpouch", 4 ],
        [ "leather_pouch", 2 ],
        [ "dump_pouch", 1 ],
        [ "purse", 2 ],
        [ "fanny", 2 ]
      ]
    ]
  },
  {
    "result": "xl_pants_survivor",
    "type": "recipe",
    "copy-from": "pants_survivor",
    "time": "15 h 45 m",
    "using": [
      [ "tailoring_kevlar_fabric", 6 ],
      [ "tailoring_cotton", 7 ],
      [ "waterproofing_plastic_sheets", 10 ],
      [ "fastener_small", 1 ]
    ],
    "components": [
      [ [ "pants_army", 2 ], [ "pants_cargo", 2 ] ],
      [
        [ "tacvest", 1 ],
        [ "legrig", 1 ],
        [ "vest", 1 ],
        [ "tool_belt", 1 ],
        [ "ragpouch", 4 ],
        [ "leather_pouch", 2 ],
        [ "dump_pouch", 1 ],
        [ "purse", 2 ],
        [ "fanny", 2 ]
      ]
    ]
  }
]
