[
  {
    "id": "spacebar",
    "type": "widget",
    "style": "sidebar",
    "label": { "str": "spacebar", "ctxt": "spacebar" },
    "width": 62,
    "separator": ": ",
    "padding": 1,
    "widgets": [
"wind_sun_rad",
      "light_moon_wind_temp_layout",
"spacebar_separator",
"enviroment_conditions_block",
      "spacebar_separator",
      "player_health_and_stasistik_block",
      "player_health_and_stasistik_block_sa",
      "spacebar_separator",
      "vital_numbers_layout",
      "spacebar_separator",
      "bodypart_armor_outer_layout",
      "bodypart_status_layout",
      "bodypart_status_sym_layout",
      "bodygraph_hp_layout",
      "spacebar_separator",
      "player_weariness_mood_block",
      "spacebar_separator",
      "xe_spacebar_mana_numbers_block",
      "xe_spacebar_mana_bar_block",
        "spacebar_separator",
      "vampire_blood_levels",
        "spacebar_separator",
      "vehicle_acf_label_layout",
      "spacebar_separator",
"spacebar_side_by_side_2", 
"spacebar_separator",
      "player_movement_block",
      "spacebar_separator",
      "player_weapon_and_martial_arts_block",
      "spacebar_separator",
      "places_compass_block_danger",
      "spacebar_separator"
    ]
  }
]
